scrapyhttppipeline/__init__.py
scrapyhttppipeline/scrapyhttppipeline.py
scrapyhttppipeline/version.py
tests/__init__.py
tests/unit/__init__.py
tests/unit/test_version.py
scrapy_http_pipeline-0.2.0.dist-info/LICENSE
scrapy_http_pipeline-0.2.0.dist-info/METADATA
scrapy_http_pipeline-0.2.0.dist-info/WHEEL
scrapy_http_pipeline-0.2.0.dist-info/top_level.txt
scrapy_http_pipeline-0.2.0.dist-info/RECORD
