Metadata-Version: 2.1
Name: scrapy-http-pipeline
Version: 0.2.0
Summary: Scrapy HTTP POST items pipeline
Home-page: https://github.com/thecodecook/scrapy-http-pipeline
Author: Vladimír Kuchár
Author-email: kuchar.vladimir@gmail.com
License: MIT License
Keywords: scrapy http pipeline export items
Platform: UNKNOWN
Classifier: Development Status :: 3 - Alpha
Classifier: Environment :: No Input/Output (Daemon)
Classifier: License :: OSI Approved :: MIT License
Classifier: Operating System :: OS Independent
Classifier: Programming Language :: Python
Requires-Dist: scrapy
Requires-Dist: requests (>=2.23.0)
Requires-Dist: six (>=1.14.0)
